{
  "节点": [
    {
      "名称": "@kit.ArkUI",
      "类型": "module",
      "描述": "模块头结点，源自 @kit 注释",
      "层级": 0,
      "注释信息": [],
      "since_version": "",
      "system_capability": "",
      "parameters": [],
      "return_description": "",
      "error_codes": [],
      "版本": "API5.1"
    },
    {
      "类型": "interface",
      "名称": "EffectComponentInterface",
      "所属模块": "@kit.ArkUI",
      "功能描述": "Provides an Effect Component, which is invisible, but setting properties on this component defines an effect template that child components can apply by setting useEffect(true).",
      "注释信息": [
        "@interface EffectComponentInterface",
        "@syscap SystemCapability.ArkUI.ArkUI.Full",
        "@systemapi",
        "@since 10"
      ],
      "层级": 1,
      "上级": "@kit.ArkUI",
      "since_version": "10",
      "system_capability": "SystemCapability.ArkUI.ArkUI.Full",
      "parameters": [],
      "return_description": "",
      "error_codes": [],
      "版本": "API5.1"
    },
    {
      "类型": "call_signature",
      "签名": "(): EffectComponentAttribute",
      "所属模块": "未知模块",
      "功能描述": "Return effectComponent.",
      "注释信息": [
        "@returns { EffectComponentAttribute }",
        "@syscap SystemCapability.ArkUI.ArkUI.Full",
        "@systemapi",
        "@since 10"
      ],
      "层级": 1,
      "上级": "EffectComponentInterface",
      "since_version": "10",
      "system_capability": "SystemCapability.ArkUI.ArkUI.Full",
      "parameters": [],
      "return_description": "",
      "error_codes": [],
      "版本": "API5.1"
    },
    {
      "类型": "class",
      "名称": "EffectComponentAttribute",
      "父类": "CommonMethod",
      "所属模块": "@kit.ArkUI",
      "功能描述": "Defines the Effect Component attribute functions.",
      "注释信息": [
        "@extends CommonMethod<EffectComponentAttribute>",
        "@syscap SystemCapability.ArkUI.ArkUI.Full",
        "@systemapi",
        "@since 10"
      ],
      "层级": 1,
      "上级": "@kit.ArkUI",
      "since_version": "10",
      "system_capability": "SystemCapability.ArkUI.ArkUI.Full",
      "parameters": [],
      "return_description": "",
      "error_codes": [],
      "版本": "API5.1"
    },
    {
      "类型": "class",
      "名称": "EffectComponentAttribute",
      "父类": "CommonMethod",
      "所属模块": "@kit.ArkUI",
      "功能描述": "Defines the Effect Component attribute functions.",
      "注释信息": [
        "@extends CommonMethod<EffectComponentAttribute>",
        "@syscap SystemCapability.ArkUI.ArkUI.Full",
        "@systemapi",
        "@since 10"
      ],
      "层级": 1,
      "上级": "@kit.ArkUI",
      "since_version": "10",
      "system_capability": "SystemCapability.ArkUI.ArkUI.Full",
      "parameters": [],
      "return_description": "",
      "error_codes": [],
      "版本": "API5.1"
    },
    {
      "所属模块": "@kit.ArkUI",
      "功能描述": "Defines Effect Component instance.",
      "注释信息": [
        "@syscap SystemCapability.ArkUI.ArkUI.Full",
        "@systemapi",
        "@since 10"
      ],
      "层级": 1,
      "上级": "@kit.ArkUI",
      "since_version": "10",
      "system_capability": "SystemCapability.ArkUI.ArkUI.Full",
      "parameters": [],
      "return_description": "",
      "error_codes": [],
      "版本": "API5.1"
    }
  ]
}