{
  "节点": [
    {
      "名称": "@kit.ArkUI",
      "类型": "module",
      "描述": "模块头结点，源自 @kit 注释",
      "层级": 0,
      "注释信息": [],
      "since_version": "",
      "system_capability": "",
      "parameters": [],
      "return_description": "",
      "error_codes": [],
      "版本": "API5.1"
    },
    {
      "类型": "interface",
      "名称": "MenuItemGroupOptions",
      "所属模块": "@kit.ArkUI",
      "功能描述": "Defines the option of MenuItemGroup.",
      "注释信息": [
        "@interface MenuItemGroupOptions",
        "@syscap SystemCapability.ArkUI.ArkUI.Full",
        "@crossplatform",
        "@atomicservice",
        "@since 11"
      ],
      "层级": 1,
      "上级": "@kit.ArkUI",
      "since_version": "11",
      "system_capability": "SystemCapability.ArkUI.ArkUI.Full",
      "parameters": [],
      "return_description": "",
      "error_codes": [],
      "版本": "API5.1"
    },
    {
      "类型": "property",
      "名称": "header",
      "属性类型": "ResourceStr | CustomBuilder",
      "所属模块": "未知模块",
      "功能描述": "Defines the header display info.",
      "注释信息": [
        "@type { ?(ResourceStr | CustomBuilder) }",
        "@syscap SystemCapability.ArkUI.ArkUI.Full",
        "@crossplatform",
        "@atomicservice",
        "@since 11"
      ],
      "层级": 1,
      "上级": "MenuItemGroupOptions",
      "since_version": "11",
      "system_capability": "SystemCapability.ArkUI.ArkUI.Full",
      "parameters": [],
      "return_description": "",
      "error_codes": [],
      "版本": "API5.1"
    },
    {
      "类型": "property",
      "名称": "footer",
      "属性类型": "ResourceStr | CustomBuilder",
      "所属模块": "未知模块",
      "功能描述": "Defines the footer display info.",
      "注释信息": [
        "@type { ?(ResourceStr | CustomBuilder) }",
        "@syscap SystemCapability.ArkUI.ArkUI.Full",
        "@crossplatform",
        "@atomicservice",
        "@since 11"
      ],
      "层级": 1,
      "上级": "MenuItemGroupOptions",
      "since_version": "11",
      "system_capability": "SystemCapability.ArkUI.ArkUI.Full",
      "parameters": [],
      "return_description": "",
      "error_codes": [],
      "版本": "API5.1"
    },
    {
      "类型": "interface",
      "名称": "MenuItemGroupInterface",
      "所属模块": "@kit.ArkUI",
      "功能描述": "Defines the MenuItemGroup Component.",
      "注释信息": [
        "@interface MenuItemGroupInterface",
        "@syscap SystemCapability.ArkUI.ArkUI.Full",
        "@crossplatform",
        "@atomicservice",
        "@since 11"
      ],
      "层级": 1,
      "上级": "@kit.ArkUI",
      "since_version": "11",
      "system_capability": "SystemCapability.ArkUI.ArkUI.Full",
      "parameters": [],
      "return_description": "",
      "error_codes": [],
      "版本": "API5.1"
    },
    {
      "类型": "call_signature",
      "签名": "(value?: MenuItemGroupOptions): MenuItemGroupAttribute",
      "所属模块": "未知模块",
      "功能描述": "Creates the MenuItemGroup component.",
      "注释信息": [
        "@param { MenuItemGroupOptions } value",
        "@returns { MenuItemGroupAttribute }",
        "@syscap SystemCapability.ArkUI.ArkUI.Full",
        "@crossplatform",
        "@atomicservice",
        "@since 11"
      ],
      "层级": 1,
      "上级": "MenuItemGroupInterface",
      "since_version": "11",
      "system_capability": "SystemCapability.ArkUI.ArkUI.Full",
      "parameters": [],
      "return_description": "",
      "error_codes": [],
      "版本": "API5.1"
    },
    {
      "类型": "class",
      "名称": "MenuItemGroupAttribute",
      "父类": "CommonMethod",
      "所属模块": "@kit.ArkUI",
      "功能描述": "Defines the MenuItemGroup component attribute functions.",
      "注释信息": [
        "@extends CommonMethod<MenuItemGroupAttribute>",
        "@syscap SystemCapability.ArkUI.ArkUI.Full",
        "@crossplatform",
        "@atomicservice",
        "@since 11"
      ],
      "层级": 1,
      "上级": "@kit.ArkUI",
      "since_version": "11",
      "system_capability": "SystemCapability.ArkUI.ArkUI.Full",
      "parameters": [],
      "return_description": "",
      "error_codes": [],
      "版本": "API5.1"
    },
    {
      "类型": "class",
      "名称": "MenuItemGroupAttribute",
      "父类": "CommonMethod",
      "所属模块": "@kit.ArkUI",
      "功能描述": "Defines the MenuItemGroup component attribute functions.",
      "注释信息": [
        "@extends CommonMethod<MenuItemGroupAttribute>",
        "@syscap SystemCapability.ArkUI.ArkUI.Full",
        "@crossplatform",
        "@atomicservice",
        "@since 11"
      ],
      "层级": 1,
      "上级": "@kit.ArkUI",
      "since_version": "11",
      "system_capability": "SystemCapability.ArkUI.ArkUI.Full",
      "parameters": [],
      "return_description": "",
      "error_codes": [],
      "版本": "API5.1"
    },
    {
      "所属模块": "@kit.ArkUI",
      "功能描述": "Defines MenuItemGroup Component instance.",
      "注释信息": [
        "@syscap SystemCapability.ArkUI.ArkUI.Full",
        "@crossplatform",
        "@atomicservice",
        "@since 11"
      ],
      "层级": 1,
      "上级": "@kit.ArkUI",
      "since_version": "11",
      "system_capability": "SystemCapability.ArkUI.ArkUI.Full",
      "parameters": [],
      "return_description": "",
      "error_codes": [],
      "版本": "API5.1"
    }
  ]
}