{
  "节点": [
    {
      "名称": "@kit.ArkUI",
      "类型": "module",
      "描述": "模块头结点，源自 @kit 注释",
      "层级": 0,
      "注释信息": [],
      "since_version": "",
      "system_capability": "",
      "parameters": [],
      "return_description": "",
      "error_codes": [],
      "版本": "API5.1"
    },
    {
      "类型": "class",
      "名称": "ComponentContent",
      "父类": "Object",
      "所属模块": "@kit.ArkUI",
      "功能描述": "Defines ComponentContent.",
      "注释信息": [
        "@extends Content",
        "@syscap SystemCapability.ArkUI.ArkUI.Full",
        "@crossplatform",
        "@atomicservice",
        "@since 12"
      ],
      "层级": 1,
      "上级": "@kit.ArkUI",
      "since_version": "12",
      "system_capability": "SystemCapability.ArkUI.ArkUI.Full",
      "parameters": [],
      "return_description": "",
      "error_codes": [],
      "版本": "API5.1"
    },
    {
      "类型": "method",
      "名称": "constructor",
      "返回值": "ComponentContent",
      "所属模块": "未知模块",
      "功能描述": "Constructor.",
      "注释信息": [
        "@param { UIContext } uiContext - uiContext used to create the ComponentContent",
        "@param { WrappedBuilder<[]> } builder - Defined the builder will be called to build ComponentContent.",
        "@syscap SystemCapability.ArkUI.ArkUI.Full",
        "@crossplatform",
        "@atomicservice",
        "@since 12"
      ],
      "层级": 1,
      "上级": "ComponentContent",
      "since_version": "12",
      "system_capability": "SystemCapability.ArkUI.ArkUI.Full",
      "parameters": [
        {
          "名称": "uiContext",
          "类型": "UIContext",
          "必填": true,
          "说明": "uiContext used to create the ComponentContent"
        },
        {
          "名称": "builder",
          "类型": "WrappedBuilder<[]>",
          "必填": true,
          "说明": "Defined the builder will be called to build ComponentContent."
        }
      ],
      "return_description": "",
      "error_codes": [],
      "版本": "API5.1"
    },
    {
      "类型": "method",
      "名称": "constructor",
      "返回值": "ComponentContent",
      "所属模块": "未知模块",
      "功能描述": "Constructor.",
      "注释信息": [
        "@param { UIContext } uiContext - uiContext used to create the ComponentContent",
        "@param { WrappedBuilder<[T]> } builder - Defined the builder will be called to build ComponentContent.",
        "@param { T } args - Parameters used to update the ComponentContent.",
        "@syscap SystemCapability.ArkUI.ArkUI.Full",
        "@crossplatform",
        "@atomicservice",
        "@since 12"
      ],
      "层级": 1,
      "上级": "ComponentContent",
      "since_version": "12",
      "system_capability": "SystemCapability.ArkUI.ArkUI.Full",
      "parameters": [
        {
          "名称": "uiContext",
          "类型": "UIContext",
          "必填": true,
          "说明": "uiContext used to create the ComponentContent"
        },
        {
          "名称": "builder",
          "类型": "WrappedBuilder<[T]>",
          "必填": true,
          "说明": "Defined the builder will be called to build ComponentContent."
        },
        {
          "名称": "args",
          "类型": "T",
          "必填": true,
          "说明": "Parameters used to update the ComponentContent."
        }
      ],
      "return_description": "",
      "error_codes": [],
      "版本": "API5.1"
    },
    {
      "类型": "method",
      "名称": "constructor",
      "返回值": "ComponentContent",
      "所属模块": "未知模块",
      "功能描述": "Constructor.",
      "注释信息": [
        "@param { UIContext } uiContext - uiContext used to create the ComponentContent",
        "@param { WrappedBuilder<[T]> } builder - Defined the builder will be called to build ComponentContent.",
        "@param { T } args - Parameters used to update the ComponentContent.",
        "@param { BuildOptions } options - Defined the options will be used when build.",
        "@syscap SystemCapability.ArkUI.ArkUI.Full",
        "@crossplatform",
        "@atomicservice",
        "@since 12"
      ],
      "层级": 1,
      "上级": "ComponentContent",
      "since_version": "12",
      "system_capability": "SystemCapability.ArkUI.ArkUI.Full",
      "parameters": [
        {
          "名称": "uiContext",
          "类型": "UIContext",
          "必填": true,
          "说明": "uiContext used to create the ComponentContent"
        },
        {
          "名称": "builder",
          "类型": "WrappedBuilder<[T]>",
          "必填": true,
          "说明": "Defined the builder will be called to build ComponentContent."
        },
        {
          "名称": "args",
          "类型": "T",
          "必填": true,
          "说明": "Parameters used to update the ComponentContent."
        },
        {
          "名称": "options",
          "类型": "BuildOptions",
          "必填": true,
          "说明": "Defined the options will be used when build."
        }
      ],
      "return_description": "",
      "error_codes": [],
      "版本": "API5.1"
    },
    {
      "类型": "method",
      "名称": "update",
      "返回值": "void",
      "所属模块": "未知模块",
      "功能描述": "Update the ComponentContent based on the provided parameters.",
      "注释信息": [
        "@param { T } args - Parameters used to update the ComponentContent, which must match the types required by the builder bound to the ComponentContent.",
        "@syscap SystemCapability.ArkUI.ArkUI.Full",
        "@crossplatform",
        "@atomicservice",
        "@since 12"
      ],
      "层级": 1,
      "上级": "ComponentContent",
      "since_version": "12",
      "system_capability": "SystemCapability.ArkUI.ArkUI.Full",
      "parameters": [
        {
          "名称": "args",
          "类型": "T",
          "必填": true,
          "说明": "Parameters used to update the ComponentContent, which must match the types required by the builder bound to the ComponentContent."
        }
      ],
      "return_description": "",
      "error_codes": [],
      "版本": "API5.1"
    },
    {
      "类型": "method",
      "名称": "reuse",
      "返回值": "void",
      "所属模块": "未知模块",
      "功能描述": "Reuse the ComponentContent based on the provided parameters.",
      "注释信息": [
        "@param { Object } [param] - Parameters for reusing ComponentContent.",
        "@syscap SystemCapability.ArkUI.ArkUI.Full",
        "@crossplatform",
        "@atomicservice",
        "@since 12"
      ],
      "层级": 1,
      "上级": "ComponentContent",
      "since_version": "12",
      "system_capability": "SystemCapability.ArkUI.ArkUI.Full",
      "parameters": [
        {
          "名称": "{",
          "类型": "any",
          "必填": true,
          "说明": "Object } [param] - Parameters for reusing ComponentContent."
        }
      ],
      "return_description": "",
      "error_codes": [],
      "版本": "API5.1"
    },
    {
      "类型": "method",
      "名称": "recycle",
      "返回值": "void",
      "所属模块": "未知模块",
      "功能描述": "Recycle the ComponentContent.",
      "注释信息": [
        "@syscap SystemCapability.ArkUI.ArkUI.Full",
        "@crossplatform",
        "@atomicservice",
        "@since 12"
      ],
      "层级": 1,
      "上级": "ComponentContent",
      "since_version": "12",
      "system_capability": "SystemCapability.ArkUI.ArkUI.Full",
      "parameters": [],
      "return_description": "",
      "error_codes": [],
      "版本": "API5.1"
    },
    {
      "类型": "method",
      "名称": "dispose",
      "返回值": "void",
      "所属模块": "未知模块",
      "功能描述": "Dispose the ComponentContent immediately.",
      "注释信息": [
        "@syscap SystemCapability.ArkUI.ArkUI.Full",
        "@crossplatform",
        "@atomicservice",
        "@since 12"
      ],
      "层级": 1,
      "上级": "ComponentContent",
      "since_version": "12",
      "system_capability": "SystemCapability.ArkUI.ArkUI.Full",
      "parameters": [],
      "return_description": "",
      "error_codes": [],
      "版本": "API5.1"
    },
    {
      "类型": "method",
      "名称": "updateConfiguration",
      "返回值": "void",
      "所属模块": "未知模块",
      "功能描述": "Notify ComponentContent to update the configuration to trigger a reload of the ComponentContent.",
      "注释信息": [
        "@syscap SystemCapability.ArkUI.ArkUI.Full",
        "@crossplatform",
        "@atomicservice",
        "@since 12"
      ],
      "层级": 1,
      "上级": "ComponentContent",
      "since_version": "12",
      "system_capability": "SystemCapability.ArkUI.ArkUI.Full",
      "parameters": [],
      "return_description": "",
      "error_codes": [],
      "版本": "API5.1"
    }
  ]
}